mrx_link/__init__.py
mrx_link/__main__.py
mrx_link/_version.py
mrx_link/cli/__init__.py
mrx_link/cli/commands.cpython-310-darwin.so
mrx_link/cli/utils.cpython-310-darwin.so
mrx_link/common/__init__.py
mrx_link/common/credential.cpython-310-darwin.so
mrx_link/common/info.cpython-310-darwin.so
mrx_link/common/singleton.cpython-310-darwin.so
mrx_link/common/system_info.cpython-310-darwin.so
mrx_link/labextension/package.json
mrx_link/labextension/schemas/mrx_link/package.json.orig
mrx_link/labextension/schemas/mrx_link/plugin.json
mrx_link/labextension/static/0.2647c707785e9270ed42.js
mrx_link/labextension/static/109.2d910176b89d9a8a200b.js
mrx_link/labextension/static/182.379f03f144f974d03cc2.js
mrx_link/labextension/static/182.379f03f144f974d03cc2.js.LICENSE.txt
mrx_link/labextension/static/212.07d65c024fab667f1059.js
mrx_link/labextension/static/213.432fd8200b0b707a9a56.js
mrx_link/labextension/static/246.9d4c075b73118249d39b.js
mrx_link/labextension/static/262.a9ba0d55d0817670aadc.js
mrx_link/labextension/static/279.623be987ae5d50c5a178.js
mrx_link/labextension/static/285.da515649078e6ae2b5f6.js
mrx_link/labextension/static/292.267b5ecaf80bffbbbf08.js
mrx_link/labextension/static/371.3afc6302f878c9b132d5.js
mrx_link/labextension/static/446.eb3d80092b97dd81c02c.js
mrx_link/labextension/static/456.001eb7abab21c7029f87.js
mrx_link/labextension/static/456.001eb7abab21c7029f87.js.LICENSE.txt
mrx_link/labextension/static/466.36b03e6f390e93e6160a.js
mrx_link/labextension/static/490.87a22ece570ef47d47e4.js
mrx_link/labextension/static/543.871a5a58517d871167d9.js
mrx_link/labextension/static/543.871a5a58517d871167d9.js.LICENSE.txt
mrx_link/labextension/static/581.6ddcf656c5a2ad332f0d.js
mrx_link/labextension/static/666.5a7133cd0f2ed15e2bb4.js
mrx_link/labextension/static/695.2abfb2f97a4f4b17a888.js
mrx_link/labextension/static/695.2abfb2f97a4f4b17a888.js.LICENSE.txt
mrx_link/labextension/static/708.3a7df963921dc6efa088.js
mrx_link-2.4.1.dist-info/METADATA
mrx_link-2.4.1.dist-info/WHEEL
mrx_link-2.4.1.dist-info/entry_points.txt
mrx_link-2.4.1.dist-info/top_level.txt
mrx_link-2.4.1.dist-info/RECORD
